birt/__init__.py
birt/abinit.py
birt_gd-0.1.47.dist-info/LICENSE
birt_gd-0.1.47.dist-info/METADATA
birt_gd-0.1.47.dist-info/WHEEL
birt_gd-0.1.47.dist-info/top_level.txt
birt_gd-0.1.47.dist-info/RECORD
