Metadata-Version: 2.1
Name: birt-gd
Version: 0.1.47
Summary: BIRT is an implementation of Beta3-irt using gradient descent.
Home-page: https://github.com/Manuelfjr/birt-gd
Author: Manuel Ferreira Junior
Author-email: ferreira.jr.ufpb@gmail.com
License: GNU General Public License v3 (GPLv3)
Project-URL: Bug Tracker, https://github.com/pypa/sampleproject/issues
Project-URL: Source Code, https://github.com/Manuelfjr/birt-gd/blob/main/src/birt/__init__.py
Classifier: Programming Language :: Python :: 3
Classifier: License :: OSI Approved :: GNU General Public License v3 (GPLv3)
Classifier: Operating System :: OS Independent
Requires-Python: >=3.6
License-File: LICENSE
Requires-Dist: numpy
Requires-Dist: tensorflow
Requires-Dist: pandas
Requires-Dist: tqdm
Requires-Dist: seaborn
Requires-Dist: matplotlib
Requires-Dist: scikit-learn
